polygon_measure/__init__.py
polygon_measure/__main__.py
polygon_measure/cli.py
polygon_measure/config.py
polygon_measure/core/__init__.py
polygon_measure/core/geometry.py
polygon_measure/core/measurement.py
polygon_measure/ui/__init__.py
polygon_measure/ui/directory_selector.py
polygon_measure/ui/display.py
polygon_measure/utils/__init__.py
polygon_measure/utils/file_utils.py
polygon_measure-2.0.2.dist-info/licenses/LICENSE
polygon_measure-2.0.2.dist-info/METADATA
polygon_measure-2.0.2.dist-info/WHEEL
polygon_measure-2.0.2.dist-info/entry_points.txt
polygon_measure-2.0.2.dist-info/top_level.txt
polygon_measure-2.0.2.dist-info/RECORD
