Metadata-Version: 2.4
Name: polygon-measure
Version: 2.0.2
Summary: Polygon measurement tool for YOLO segmentation datasets
Home-page: https://github.com/Vicellken/polygon-measure
Author: yifeigu
Project-URL: Homepage, https://github.com/Vicellken/polygon-measure
Project-URL: Bug Reports, https://github.com/Vicellken/polygon-measure/issues
Project-URL: Source, https://github.com/Vicellken/polygon-measure
Keywords: yolo,polygon,measurement,computer-vision,annotation,segmentation
Classifier: Intended Audience :: Science/Research
Classifier: Operating System :: OS Independent
Classifier: Programming Language :: Python :: 3
Classifier: Programming Language :: Python :: 3.9
Classifier: Topic :: Scientific/Engineering :: Image Processing
Classifier: Topic :: Scientific/Engineering :: Artificial Intelligence
Requires-Python: >=3.9
License-File: LICENSE
Requires-Dist: opencv-python>=4.5.0
Requires-Dist: numpy>=1.19.0
Requires-Dist: pandas>=1.1.0
Requires-Dist: scipy>=1.5.0
Dynamic: home-page
Dynamic: license-file
Dynamic: requires-python
